nonebot_plugin_warthunder_player_check/__init__.py
nonebot_plugin_warthunder_player_check-0.1.3.dist-info/METADATA
nonebot_plugin_warthunder_player_check-0.1.3.dist-info/WHEEL
nonebot_plugin_warthunder_player_check-0.1.3.dist-info/top_level.txt
nonebot_plugin_warthunder_player_check-0.1.3.dist-info/RECORD
