Metadata-Version: 2.1
Name: nonebot-plugin-warthunder-player-check
Version: 0.1.3
Summary: nonebot2 plugin
Home-page: https://github.com/0Neptune0/nonebot-plugin-warthunder-player-check
Author: 00.Neptune.00
Author-email: neptune.0@qq.com
License: GNU General Public License v3.0
Platform: UNKNOWN
Requires-Python: >=3.8
Requires-Dist: nonebot2 (>=2.0.0)
Requires-Dist: nonebot-adapter-onebot (>=2.2.3)
Requires-Dist: playwright
Requires-Dist: beautifulsoup4
Requires-Dist: pillow
